obex_wrapper/__init__.py
obex_wrapper/obex.py
obex_wrapper-0.1.17.dist-info/METADATA
obex_wrapper-0.1.17.dist-info/WHEEL
obex_wrapper-0.1.17.dist-info/RECORD
