Metadata-Version: 2.1
Name: obex-wrapper
Version: 0.1.17
Summary: Obex python client
Author: Sriram Keelveedhi
Author-email: ram@obex.dev
Requires-Python: >=3.8,<4.0
Classifier: Programming Language :: Python :: 3
Classifier: Programming Language :: Python :: 3.8
Classifier: Programming Language :: Python :: 3.9
Classifier: Programming Language :: Python :: 3.10
Classifier: Programming Language :: Python :: 3.11
Classifier: Programming Language :: Python :: 3.12
Requires-Dist: boto3 (>=1.34.49,<2.0.0)
Requires-Dist: detoxify (==0.5.2)
Requires-Dist: opentelemetry-api (>=1.23.0,<2.0.0)
Requires-Dist: opentelemetry-distro (>=0.44b0,<0.45)
Requires-Dist: opentelemetry-exporter-otlp (>=1.23.0,<2.0.0)
Requires-Dist: opentelemetry-sdk (>=1.23.0,<2.0.0)
Requires-Dist: presidio_analyzer (>=2.2.353,<3.0.0)
Requires-Dist: torch (>=2.2.1,<3.0.0)
Requires-Dist: transformers (>=4.39.1,<5.0.0)
